pyclibrary/__init__.py
pyclibrary/c_library.py
pyclibrary/c_parser.py
pyclibrary/errors.py
pyclibrary/init.py
pyclibrary/utils.py
pyclibrary/version.py
pyclibrary/backends/__init__.py
pyclibrary/backends/ctypes.py
pyclibrary/headers/README
pyclibrary/headers/WinDefs.cache
pyclibrary/headers/update_WinDefs.py
pyclibrary/thirdparty/__init__.py
pyclibrary/thirdparty/find_library.py
pyclibrary-0.2.2.dist-info/AUTHORS
pyclibrary-0.2.2.dist-info/LICENSE
pyclibrary-0.2.2.dist-info/METADATA
pyclibrary-0.2.2.dist-info/WHEEL
pyclibrary-0.2.2.dist-info/top_level.txt
pyclibrary-0.2.2.dist-info/RECORD
