Metadata-Version: 2.1
Name: pyclibrary
Version: 0.2.2
Summary: C binding automation
Home-page: http://github.com/MatthieuDartiailh/pyclibrary
Author: PyCLibrary Developers
Author-email: m.dartiailh@gmail.com
License: MIT
Download-URL: http://github.com/MatthieuDartiailh/pyclibrary/tarball/master
Keywords: C binding automation
Platform: UNKNOWN
Classifier: Development Status :: 3 - Alpha
Classifier: Environment :: Console
Classifier: License :: OSI Approved :: MIT License
Classifier: Natural Language :: English
Classifier: Operating System :: OS Independent
Classifier: Topic :: Software Development :: Libraries :: Python Modules
Classifier: Programming Language :: Python :: 3.6
Classifier: Programming Language :: Python :: 3.7
Classifier: Programming Language :: Python :: 3.8
Classifier: Programming Language :: Python :: 3.9
Classifier: Programming Language :: Python :: 3.10
Requires-Dist: pyparsing <4,>=2.3.1
